HexText/__init__.py
HexText-0.1.0.dist-info/METADATA
HexText-0.1.0.dist-info/WHEEL
HexText-0.1.0.dist-info/top_level.txt
HexText-0.1.0.dist-info/RECORD
