Metadata-Version: 2.1
Name: HexText
Version: 0.1.0
Summary: Create Coloured/Gradient Text In Python
Home-page: https://github.com/SirScripter/HexText
Author: ZakRehman
Author-email: zaksteryt@gmail.com
Classifier: Programming Language :: Python :: 3
Classifier: License :: OSI Approved :: MIT License
Classifier: Operating System :: OS Independent
Requires-Python: >=3.6
